django_html5croppingtools-0.1.3.dist-info/RECORD
django_html5croppingtools-0.1.3.dist-info/DESCRIPTION.rst
django_html5croppingtools-0.1.3.dist-info/WHEEL
django_html5croppingtools-0.1.3.dist-info/top_level.txt
django_html5croppingtools-0.1.3.dist-info/metadata.json
django_html5croppingtools-0.1.3.dist-info/METADATA
html5croppingtools/imagecrop.py
html5croppingtools/fields.py
html5croppingtools/forms.py
html5croppingtools/widgets.py
html5croppingtools/tests.py
html5croppingtools/__init__.py
html5croppingtools/static/html5croppingtools/html5crop.js
html5croppingtools/static/html5croppingtools/jcrop/MIT-LICENSE.txt
html5croppingtools/static/html5croppingtools/jcrop/index.html
html5croppingtools/static/html5croppingtools/jcrop/README.md
html5croppingtools/static/html5croppingtools/jcrop/css/Jcrop.gif
html5croppingtools/static/html5croppingtools/jcrop/css/jquery.Jcrop.css
html5croppingtools/static/html5croppingtools/jcrop/css/jquery.Jcrop.min.css
html5croppingtools/static/html5croppingtools/jcrop/js/jquery.Jcrop.js
html5croppingtools/static/html5croppingtools/jcrop/js/jquery.Jcrop.min.js
html5croppingtools/static/html5croppingtools/jcrop/js/jquery.min.js
html5croppingtools/static/html5croppingtools/jcrop/js/jquery.color.js
html5croppingtools/templatetags/croppingtools_extra.py
html5croppingtools/templatetags/__init__.py
html5croppingtools/templatetags/__pycache__/croppingtools_extra.cpython-34.pyc
html5croppingtools/templatetags/__pycache__/__init__.cpython-34.pyc
