Metadata-Version: 2.0
Name: django-html5croppingtools
Version: 0.1.3
Summary: A simple Django app to crop and resize images
Home-page: https://github.com/iraklikhitarishvili/html5croppingtools
Author: irakli khitarishvili
Author-email: irakli11992@gmail.com
License: BSD License
Platform: UNKNOWN
Classifier: Development Status :: 4 - Beta
Classifier: Environment :: Web Environment
Classifier: Framework :: Django :: 1.7
Classifier: Framework :: Django :: 1.8
Classifier: Programming Language :: Python :: 3 :: Only
Classifier: Intended Audience :: Developers
Classifier: License :: OSI Approved :: BSD License
Classifier: Operating System :: OS Independent
Classifier: Topic :: Internet :: WWW/HTTP
Classifier: Topic :: Internet :: WWW/HTTP :: Dynamic Content
Requires-Dist: pillow
